bazos/__init__.py
bazos/bazos.py
bazos/core/__init__.py
bazos/core/settings.py
bazos/info/__init__.py
bazos/info/product.py
bazos/info/rubric_category.py
bazos/info/user.py
bazos/info/tests/__init__.py
bazos/shared/__init__.py
bazos/shared/utils.py
bazos/shared/tests/__init__.py
bazos/tests/__init__.py
bazos-0.0.7.dist-info/METADATA
bazos-0.0.7.dist-info/WHEEL
bazos-0.0.7.dist-info/entry_points.txt
bazos-0.0.7.dist-info/top_level.txt
bazos-0.0.7.dist-info/RECORD
