Metadata-Version: 2.1
Name: bazos
Version: 0.0.7
Summary: Bazos API, that allows you to scrape bazos and upload products to bazos website.
Author: Zdenek Lapes
License: MIT
Classifier: Programming Language :: Python :: 3
Classifier: License :: OSI Approved :: MIT License
Classifier: Development Status :: 1 - Planning
Classifier: Intended Audience :: Developers
Classifier: Operating System :: Unix
Classifier: Operating System :: MacOS :: MacOS X
Requires-Python: >=3.10
